kingland_team/__init__.py
kingland_team-0.1.0.dist-info/METADATA
kingland_team-0.1.0.dist-info/WHEEL
kingland_team-0.1.0.dist-info/entry_points.txt
kingland_team-0.1.0.dist-info/RECORD
