Metadata-Version: 2.4
Name: kingland-team
Version: 0.1.0
Summary: Add your description here
Author-email: Oliver <linbaozhang@aliyun.com>
Requires-Python: >=3.12
Requires-Dist: mcp[cli]>=1.9.4
